{
  "light": {
    "background": "#F7F8FC",
    "foreground": "#18212F",
    "surface": "#FFFFFF",
    "surfaceAlt": "#FFF4F7",
    "muted": "#667085",
    "mutedLight": "#98A2B3",
    "border": "#E7EAF0",
    "borderFocus": "#F3A6C0",
    "divider": "#E2E8F0",
    "accent": "#E85D8C",
    "accentSoft": "rgba(232, 93, 140, 0.14)",
    "accentSoft2": "rgba(232, 93, 140, 0.08)",
    "accentBorder": "#F3A6C0",
    "titleGradientFrom": "#DB2777",
    "titleGradientTo": "#F472B6",
    "scanFrom": "#E85D8C",
    "scanTo": "#F59EBC",
    "success": "#16A34A",
    "successSoft": "#DCFCE7",
    "warning": "#D97706",
    "warningSoft": "#FEF3C7",
    "danger": "#DC2626",
    "dangerSoft": "#FEE2E2",
    "info": "#0284C7",
    "infoSoft": "rgba(2, 132, 199, 0.12)",
    "onAccent": "#FFFFFF",
    "onAccentMuted": "rgba(255, 255, 255, 0.86)",
    "onDanger": "#FFFFFF",
    "scrim": "rgba(15, 23, 42, 0.45)",
    "scrimSoft": "rgba(15, 23, 42, 0.35)",
    "shadow": "#0F172A"
  },
  "dark": {
    "background": "#0B1220",
    "foreground": "#F8FAFC",
    "surface": "#111827",
    "surfaceAlt": "#1A2335",
    "muted": "#CBD5E1",
    "mutedLight": "#94A3B8",
    "border": "#334155",
    "borderFocus": "#93C5FD",
    "divider": "#243247",
    "accent": "#60A5FA",
    "accentSoft": "rgba(96, 165, 250, 0.18)",
    "accentSoft2": "rgba(96, 165, 250, 0.10)",
    "accentBorder": "#93C5FD",
    "titleGradientFrom": "#60A5FA",
    "titleGradientTo": "#3B82F6",
    "scanFrom": "#60A5FA",
    "scanTo": "#93C5FD",
    "success": "#4ADE80",
    "successSoft": "rgba(74, 222, 128, 0.16)",
    "warning": "#F59E0B",
    "warningSoft": "rgba(245, 158, 11, 0.16)",
    "danger": "#F87171",
    "dangerSoft": "rgba(248, 113, 113, 0.16)",
    "info": "#38BDF8",
    "infoSoft": "rgba(56, 189, 248, 0.18)",
    "onAccent": "#FFFFFF",
    "onAccentMuted": "rgba(255, 255, 255, 0.86)",
    "onDanger": "#FFFFFF",
    "scrim": "rgba(2, 6, 23, 0.72)",
    "scrimSoft": "rgba(2, 6, 23, 0.52)",
    "shadow": "#000000"
  }
}
